tcr_deep_insight/__init__.py
tcr_deep_insight/_compat.py
tcr_deep_insight/_metadata.py
tcr_deep_insight/_version.py
tcr_deep_insight/data/__init__.py
tcr_deep_insight/data/_dataloader.py
tcr_deep_insight/data/fasta/hla_prot.fasta
tcr_deep_insight/data/fasta/hla_pseudo.fasta
tcr_deep_insight/data/imgt/TRAJ.fasta
tcr_deep_insight/data/imgt/TRAV.fasta
tcr_deep_insight/data/imgt/TRBD.fasta
tcr_deep_insight/data/imgt/TRBJ.fasta
tcr_deep_insight/data/imgt/TRBV.fasta
tcr_deep_insight/externals/flash_4.py
tcr_deep_insight/model/__init__.py
tcr_deep_insight/model/_constants.py
tcr_deep_insight/model/_model_utils.py
tcr_deep_insight/model/modeling_bert/__init__.py
tcr_deep_insight/model/modeling_bert/_collator.py
tcr_deep_insight/model/modeling_bert/_config.py
tcr_deep_insight/model/modeling_bert/_defaults.py
tcr_deep_insight/model/modeling_bert/_layers.py
tcr_deep_insight/model/modeling_bert/_model.py
tcr_deep_insight/model/modeling_bert/_trainer.py
tcr_deep_insight/model/modeling_bert/externals/bert_layers.py
tcr_deep_insight/model/modeling_bert/externals/bert_padding.py
tcr_deep_insight/model/modeling_bert/externals/configuration_bert.py
tcr_deep_insight/model/modeling_bert/externals/flash_attn_triton.py
tcr_deep_insight/model/modeling_causal_lm/__init__.py
tcr_deep_insight/model/modeling_causal_lm/models/_config.py
tcr_deep_insight/model/modeling_causal_lm/models/_model.py
tcr_deep_insight/model/modeling_causal_lm/models/_modeling_utils.py
tcr_deep_insight/model/modeling_causal_lm/models/_primitives.py
tcr_deep_insight/model/tokenizers/__init__.py
tcr_deep_insight/model/tokenizers/_tokenizer.py
tcr_deep_insight/model/tokenizers/tokenizer.json
tcr_deep_insight/pipeline/__init__.py
tcr_deep_insight/pipeline/_gex_pipeline.py
tcr_deep_insight/pipeline/_tcr_pipeline.py
tcr_deep_insight/pipeline/_tr_gx_pipeline.py
tcr_deep_insight/plotting/__init__.py
tcr_deep_insight/plotting/_palette.py
tcr_deep_insight/plotting/_plotting.py
tcr_deep_insight/plotting/fonts/Arial.ttf
tcr_deep_insight-1.0.2.1.dist-info/LICENSE
tcr_deep_insight-1.0.2.1.dist-info/METADATA
tcr_deep_insight-1.0.2.1.dist-info/WHEEL
tcr_deep_insight-1.0.2.1.dist-info/dependency_links.txt
tcr_deep_insight-1.0.2.1.dist-info/top_level.txt
tcr_deep_insight-1.0.2.1.dist-info/RECORD
