Metadata-Version: 2.1
Name: tcr_deep_insight
Version: 1.0.2.1
Summary: tcr_deep_insight
Home-page: https://github.com/WanluLiuLab/TCR-DeepInsight
Author: Ziwei Xue
Author-email: ziwei.21@intl.zju.edu.cn
Requires-Python: >=3.9
License-File: LICENSE
Requires-Dist: scatlasvae >=1.0.5
Requires-Dist: numba ==0.57.1
Requires-Dist: numpy ==1.21.6
Requires-Dist: pandas ==1.4.2
Requires-Dist: omegaconf ==2.3.0
Requires-Dist: scikit-image ==0.20.0
Requires-Dist: transformers ==4.17.0
Requires-Dist: datasets ==2.1.0
Requires-Dist: huggingface-hub ==0.27.1
Requires-Dist: requests ==2.32.3
Requires-Dist: pyarrow ==18.1.0
Requires-Dist: anndata ==0.8.0
Requires-Dist: scanpy ==1.8.1
Requires-Dist: scikit-learn ==0.24.1
Requires-Dist: matplotlib ==3.3.4
Requires-Dist: einops ==0.4.1
Requires-Dist: biopython ==1.79
Requires-Dist: seaborn ==0.12.2
Requires-Dist: tabulate ==0.9.0
Requires-Dist: umap-learn ==0.5.1
Requires-Dist: torch ==1.13.1
Requires-Dist: logomaker
Requires-Dist: tqdm
Requires-Dist: tqdm-joblib
Provides-Extra: cpu
Requires-Dist: faiss-cpu ==1.7.2 ; extra == 'cpu'
Provides-Extra: docs
Requires-Dist: sphinx ==7.3.7 ; extra == 'docs'
Requires-Dist: nbsphinx ; extra == 'docs'
Requires-Dist: sphinx-rtd-theme ; extra == 'docs'
Requires-Dist: sphinx-hoverxref ; extra == 'docs'
Provides-Extra: gpu
Requires-Dist: faiss-gpu ==1.7.2 ; extra == 'gpu'
